ansible_galaxy_win/__init__.py
ansible_galaxy_win/galaxy_win.py
ansible_galaxy_win-1.1.dist-info/METADATA
ansible_galaxy_win-1.1.dist-info/WHEEL
ansible_galaxy_win-1.1.dist-info/entry_points.txt
ansible_galaxy_win-1.1.dist-info/top_level.txt
ansible_galaxy_win-1.1.dist-info/RECORD
