Metadata-Version: 2.4
Name: ansible-galaxy-win
Version: 1.1
Summary: Allows for downloading of Ansible collections on Windows
Author-email: Annon <annonm@gmail.com>
Requires-Dist: ansible
